oneline/__init__.py
oneline/convertor/__init__.py
oneline/convertor/hash.py
oneline/core/__init__.py
oneline/core/error.py
oneline/core/onedata.py
oneline/core/oneseries.py
oneline/core/plot.py
oneline/io/__init__.py
oneline/io/file_input.py
oneline/io/io.py
oneline/machinelearning/__init__.py
oneline/machinelearning/average_meter.py
oneline/machinelearning/machine_learning.py
oneline/machinelearning/neural_network.py
oneline/tools/__init__.py
oneline/tools/compat.py
oneline/tools/isornot.py
one_line-0.2.7.dist-info/LICENSE
one_line-0.2.7.dist-info/METADATA
one_line-0.2.7.dist-info/WHEEL
one_line-0.2.7.dist-info/top_level.txt
one_line-0.2.7.dist-info/RECORD
