Metadata-Version: 2.1
Name: one-line
Version: 0.2.7
Summary: Make every step oneLine.
Home-page: https://github.com/clarenceehsu/oneLine
Author: Zeesain Tsui
Author-email: clarenceehsu@163.com
License: UNKNOWN
Platform: UNKNOWN
Classifier: License :: OSI Approved :: MIT License
Classifier: Programming Language :: Python :: 3
Classifier: Programming Language :: Python :: 3.4
Classifier: Programming Language :: Python :: 3.5
Classifier: Programming Language :: Python :: 3.6
Classifier: Programming Language :: Python :: 3.7
Classifier: Programming Language :: Python :: 3.8
Classifier: Programming Language :: Python :: 3.9
Requires-Dist: pandas
